better_git_cli/__init__.py
better_git_cli/helpers.py
better_git_cli/languages.py
better_git_cli/main.py
better_git_cli/new_repo.py
better_git_cli/options.py
better_git_cli/repos.py
better_git_cli/sshkeys.py
better_git_cli/user.py
bettergitcli-1.3.0.dist-info/entry_points.txt
bettergitcli-1.3.0.dist-info/LICENSE
bettergitcli-1.3.0.dist-info/WHEEL
bettergitcli-1.3.0.dist-info/METADATA
bettergitcli-1.3.0.dist-info/RECORD
