Metadata-Version: 2.1
Name: bettergitcli
Version: 1.3.0
Summary: GitHub CLI with intuitive UI and keyboard controls!
Home-page: https://github.com/PiotrRut/BetterGitCLI
License: GPL-3.0-only
Author: Piotr Rutkowski
Requires-Python: >=3.6,<4.0
Classifier: License :: OSI Approved :: GNU General Public License v3 (GPLv3)
Classifier: Programming Language :: Python :: 3
Classifier: Programming Language :: Python :: 3.6
Classifier: Programming Language :: Python :: 3.7
Classifier: Programming Language :: Python :: 3.8
Classifier: Programming Language :: Python :: 3.9
Requires-Dist: PyGithub
Requires-Dist: PyInquirer
Requires-Dist: colorama
Project-URL: Repository, https://github.com/PiotrRut/BetterGitCLI
